fuxictr/__init__.py
fuxictr/autotuner.py
fuxictr/features.py
fuxictr/metrics.py
fuxictr/utils.py
fuxictr/version.py
fuxictr/datasets/__init__.py
fuxictr/datasets/avazu.py
fuxictr/datasets/criteo.py
fuxictr/datasets/kkbox.py
fuxictr/preprocess/__init__.py
fuxictr/preprocess/build_dataset.py
fuxictr/preprocess/feature_processor.py
fuxictr/preprocess/normalizer.py
fuxictr/preprocess/tokenizer.py
fuxictr/pytorch/__init__.py
fuxictr/pytorch/torch_utils.py
fuxictr/pytorch/dataloaders/__init__.py
fuxictr/pytorch/dataloaders/npz_block_dataloader.py
fuxictr/pytorch/dataloaders/npz_dataloader.py
fuxictr/pytorch/dataloaders/parquet_block_dataloader.py
fuxictr/pytorch/dataloaders/parquet_dataloader.py
fuxictr/pytorch/dataloaders/rank_dataloader.py
fuxictr/pytorch/layers/__init__.py
fuxictr/pytorch/layers/activations.py
fuxictr/pytorch/layers/pooling.py
fuxictr/pytorch/layers/attentions/__init__.py
fuxictr/pytorch/layers/attentions/dot_product_attention.py
fuxictr/pytorch/layers/attentions/squeeze_excitation.py
fuxictr/pytorch/layers/attentions/target_attention.py
fuxictr/pytorch/layers/blocks/__init__.py
fuxictr/pytorch/layers/blocks/factorization_machine.py
fuxictr/pytorch/layers/blocks/logistic_regression.py
fuxictr/pytorch/layers/blocks/mlp_block.py
fuxictr/pytorch/layers/embeddings/__init__.py
fuxictr/pytorch/layers/embeddings/feature_embedding.py
fuxictr/pytorch/layers/embeddings/pretrained_embedding.py
fuxictr/pytorch/layers/interactions/__init__.py
fuxictr/pytorch/layers/interactions/bilinear_interaction.py
fuxictr/pytorch/layers/interactions/compressed_interaction_net.py
fuxictr/pytorch/layers/interactions/cross_net.py
fuxictr/pytorch/layers/interactions/holographic_interaction.py
fuxictr/pytorch/layers/interactions/inner_product.py
fuxictr/pytorch/layers/interactions/interaction_machine.py
fuxictr/pytorch/models/__init__.py
fuxictr/pytorch/models/multitask_model.py
fuxictr/pytorch/models/rank_model.py
fuxictr/tensorflow/__init__.py
fuxictr/tensorflow/tf_utils.py
fuxictr-2.3.9.dist-info/LICENSE
fuxictr-2.3.9.dist-info/METADATA
fuxictr-2.3.9.dist-info/WHEEL
fuxictr-2.3.9.dist-info/top_level.txt
fuxictr-2.3.9.dist-info/RECORD
