Metadata-Version: 2.1
Name: fuxictr
Version: 2.3.9
Summary: A configurable, tunable, and reproducible library for CTR prediction
Home-page: https://github.com/reczoo/FuxiCTR
Author: RECZOO
Author-email: reczoo@users.noreply.github.com
License: Apache-2.0 License
Download-URL: https://github.com/reczoo/FuxiCTR/tags
Keywords: ctr prediction,recommender systems,ctr,cvr,pytorch
Platform: UNKNOWN
Classifier: License :: OSI Approved :: Apache Software License
Classifier: Operating System :: OS Independent
Classifier: Intended Audience :: Developers
Classifier: Intended Audience :: Education
Classifier: Intended Audience :: Science/Research
Classifier: Programming Language :: Python :: 3
Classifier: Topic :: Scientific/Engineering
Classifier: Topic :: Scientific/Engineering :: Artificial Intelligence
Classifier: Topic :: Software Development
Classifier: Topic :: Software Development :: Libraries
Classifier: Topic :: Software Development :: Libraries :: Python Modules
Requires-Python: >=3.6
License-File: LICENSE
Requires-Dist: keras-preprocessing
Requires-Dist: pandas
Requires-Dist: PyYAML>=5.1
Requires-Dist: scikit-learn
Requires-Dist: numpy
Requires-Dist: h5py
Requires-Dist: tqdm
Requires-Dist: pyarrow
Requires-Dist: polars
